setup.py
context/__init__.py
context/api.py
context.api.egg-info/PKG-INFO
context.api.egg-info/SOURCES.txt
context.api.egg-info/dependency_links.txt
context.api.egg-info/namespace_packages.txt
context.api.egg-info/requires.txt
context.api.egg-info/top_level.txt
context.api.egg-info/zip-safe