Metadata-Version: 1.1
Name: context.api
Version: 0.0
Summary: A Python API for the Context profiler
Home-page: http://code.shishnet.org/context
Author: Shish
Author-email: shish+context@shishnet.org
License: UNKNOWN
Keywords: profile
Platform: UNKNOWN
Classifier: Programming Language :: Python
